musclebeachtools/__init__.py
musclebeachtools/_version.py
musclebeachtools/mbt_neurons.py
musclebeachtools/mbt_sorter_interface_out.py
musclebeachtools/mbt_spkinterface_out.py
musclebeachtools-1.4.2.dist-info/LICENSE
musclebeachtools-1.4.2.dist-info/METADATA
musclebeachtools-1.4.2.dist-info/WHEEL
musclebeachtools-1.4.2.dist-info/top_level.txt
musclebeachtools-1.4.2.dist-info/RECORD
