Metadata-Version: 2.1
Name: musclebeachtools
Version: 1.4.2
Summary: This package used to analyze neuron data, from basic plotting               (ISI histograms, firing rate, cross corr), to hard core               computational work (ising models, branching ratios, etc).
Home-page: https://github.com/hengenlab/musclebeachtools
Download-URL: https://github.com/hengenlab/musclebeachtools
Author: Keith Hengen, Sahara Ensley, Kiran Bhaskaran-Nair           (Hengen Lab Washington University in St. Louis)
Author-email: 
Maintainer: Kiran Bhaskaran-Nair, Sahara Ensley, Keith Hengen,           (Hengen Lab Washington University in St. Louis)
Maintainer-email: 
Keywords: musclebeachtools,neuroscience,electrophysiology
Classifier: Natural Language :: English
Classifier: Programming Language :: Python :: 3
License-File: LICENSE
Requires-Dist: ipython
Requires-Dist: numpy
Requires-Dist: matplotlib
Requires-Dist: seaborn
Requires-Dist: pandas
Requires-Dist: joblib
Requires-Dist: scipy
Requires-Dist: scikit-learn
Requires-Dist: mrestimator
Requires-Dist: neuraltoolkit
Requires-Dist: xgboost
